decorata/__init__.py
decorata/augmentations.py
decorata/data.py
decorata/kelvin_table.json
decorata/transforms.py
decorata/utils/__init__.py
decorata/utils/chart.py
decorata-0.0.1a4.dist-info/LICENSE
decorata-0.0.1a4.dist-info/METADATA
decorata-0.0.1a4.dist-info/WHEEL
decorata-0.0.1a4.dist-info/top_level.txt
decorata-0.0.1a4.dist-info/RECORD
