Metadata-Version: 2.1
Name: decorata
Version: 0.0.1a4
Summary: Convenient dataset maker
Home-page: https://github.com/jinoan/decorata.git
Author: jinoan
Author-email: jinoan89@gmail.com
License: UNKNOWN
Platform: UNKNOWN
Classifier: Programming Language :: Python :: 3
Classifier: License :: OSI Approved :: MIT License
Requires-Python: >=3.6
License-File: LICENSE
